lawsql_cases_justices/__init__.py
lawsql_cases_justices/__main__.py
lawsql_cases_justices/api.py
lawsql_cases_justices/config.py
lawsql_cases_justices/patterns.py
lawsql_cases_justices/surname.py
lawsql_cases_justices/typos.py
lawsql_cases_justices/utils.py
lawsql_cases_justices-0.0.5.dist-info/WHEEL
lawsql_cases_justices-0.0.5.dist-info/METADATA
lawsql_cases_justices-0.0.5.dist-info/RECORD
