Metadata-Version: 2.1
Name: lawsql-cases-justices
Version: 0.0.5
Summary: Get justices from yaml file; updates local database.
Author: Marcelino G. Veloso III
Author-email: mars@veloso.one
Requires-Python: >=3.9,<4.0
Classifier: Programming Language :: Python :: 3
Classifier: Programming Language :: Python :: 3.9
Classifier: Programming Language :: Python :: 3.10
Requires-Dist: PyYAML (>=6.0,<7.0)
Requires-Dist: Unidecode (>=1.2.0,<2.0.0)
Requires-Dist: httpx (>=0.22.0,<0.23.0)
Requires-Dist: python-dotenv (>=0.19.2,<0.20.0)
Requires-Dist: sqlite-utils (>=3.26,<4.0)
